{"_id":"BJyzhBFQW","title":"Iterator","body":{"entityMap":{},"blocks":[{"key":"ag6qs","text":"Iterator","type":"header-one","depth":0,"inlineStyleRanges":[],"entityRanges":[],"data":{}},{"key":"5up77","text":"yo={\"x\":10,\"y\":20}","type":"custom-code-block-python","depth":0,"inlineStyleRanges":[],"entityRanges":[],"data":{}},{"key":"b4ref","text":"for val in iter(yo)","type":"custom-code-block-python","depth":0,"inlineStyleRanges":[],"entityRanges":[],"data":{}},{"key":"cmfmr","text":"    print(val)","type":"custom-code-block-python","depth":0,"inlineStyleRanges":[],"entityRanges":[],"data":{}},{"key":"fbi1h","text":"    this prints x and y.","type":"ordered-list-item","depth":0,"inlineStyleRanges":[],"entityRanges":[],"data":{}},{"key":"9apmf","text":"here yo is a dictionary ","type":"ordered-list-item","depth":0,"inlineStyleRanges":[],"entityRanges":[],"data":{}},{"key":"6ak7b","text":"we can print the values in the following way","type":"custom-code-block-python","depth":0,"inlineStyleRanges":[],"entityRanges":[],"data":{}},{"key":"f0apl","text":"for val in iter(yo)","type":"custom-code-block-python","depth":0,"inlineStyleRanges":[],"entityRanges":[],"data":{}},{"key":"74u8e","text":"    print(yo[val])","type":"custom-code-block-python","depth":0,"inlineStyleRanges":[],"entityRanges":[],"data":{}},{"key":"dlc6j","text":"","type":"header-one","depth":0,"inlineStyleRanges":[],"entityRanges":[],"data":{}},{"key":"59kd9","text":"","type":"unstyled","depth":0,"inlineStyleRanges":[],"entityRanges":[],"data":{}}]},"dateCreated":"2017-06-22T13:54:14.802Z","lastUpdated":"2017-06-22T14:02:45.188Z"}
