{"_id":"SyqBwRDZ4","title":"Enjoy the positive things in life","body":{"entityMap":{},"blocks":[{"key":"ag6qs","text":"Enjoy the positive things in life","type":"header-one","depth":0,"inlineStyleRanges":[],"entityRanges":[],"data":{}},{"key":"43nl8","text":"We should spend most of our time enjoying the things we love rather than thinking about things we hate.","type":"header-two","depth":0,"inlineStyleRanges":[],"entityRanges":[],"data":{}},{"key":"59kd9","text":"","type":"unstyled","depth":0,"inlineStyleRanges":[],"entityRanges":[],"data":{}}]},"dateCreated":"2018-12-31T17:52:01.995Z","lastUpdated":"2018-12-31T17:53:33.172Z"}
