{"_id":"ryVk6G9hX","title":"Delete a column","body":{"entityMap":{},"blocks":[{"key":"ag6qs","text":"Delete a column","type":"header-one","depth":0,"inlineStyleRanges":[],"entityRanges":[],"data":{}},{"key":"9olei","text":"df = df.drop('column_name',1)","type":"custom-code-block-python","depth":0,"inlineStyleRanges":[],"entityRanges":[],"data":{}},{"key":"59kd9","text":"here 1 is the axis number","type":"header-two","depth":0,"inlineStyleRanges":[],"entityRanges":[],"data":{}}]},"dateCreated":"2018-11-02T18:52:11.670Z","lastUpdated":"2018-11-02T18:52:55.395Z"}
